pitao/__init__.py
pitao/cli.py
pitao/logger.py
pitao/parser.py
pitao/pt2py.py
pitao/py2pt.py
pitao-0.1.0.dist-info/METADATA
pitao-0.1.0.dist-info/WHEEL
pitao-0.1.0.dist-info/entry_points.txt
pitao-0.1.0.dist-info/RECORD
