Metadata-Version: 2.4
Name: pitao
Version: 0.1.0
Summary: Python com palavras reservadas em Português
Project-URL: Homepage, https://github.com/ivancrneto/pitao
Project-URL: Repository, https://github.com/ivancrneto/pitao
Author: Ivan Neto
License: MIT
Keywords: brasil,education,portuguese,preprocessor,python
Classifier: Development Status :: 3 - Alpha
Classifier: Intended Audience :: Developers
Classifier: Intended Audience :: Education
Classifier: License :: OSI Approved :: MIT License
Classifier: Natural Language :: Portuguese (Brazilian)
Classifier: Programming Language :: Python :: 3
Classifier: Programming Language :: Python :: 3.8
Classifier: Programming Language :: Python :: 3.9
Classifier: Programming Language :: Python :: 3.10
Classifier: Programming Language :: Python :: 3.11
Classifier: Programming Language :: Python :: 3.12
Classifier: Programming Language :: Python :: 3.13
Classifier: Topic :: Education
Classifier: Topic :: Software Development :: Pre-processors
Requires-Python: >=3.8
